ferelight/__init__.py
ferelight/__main__.py
ferelight/encoder.py
ferelight/typing_utils.py
ferelight/util.py
ferelight/controllers/__init__.py
ferelight/controllers/default_controller.py
ferelight/controllers/security_controller.py
ferelight/models/__init__.py
ferelight/models/base_model.py
ferelight/models/multimediaobject.py
ferelight/models/multimediasegment.py
ferelight/models/objectinfos_post_request.py
ferelight/models/query_post_request.py
ferelight/models/querybyexample_post_request.py
ferelight/models/scoredsegment.py
ferelight/models/segmentbytime_post200_response.py
ferelight/models/segmentbytime_post_request.py
ferelight/models/segmentinfos_post_request.py
ferelight/openapi/openapi.yaml
ferelight/test/__init__.py
ferelight/test/test_default_controller.py
ferelight-1.3.0.dist-info/licenses/LICENSE
tests/__init__.py
tests/test_import.py
ferelight-1.3.0.dist-info/METADATA
ferelight-1.3.0.dist-info/WHEEL
ferelight-1.3.0.dist-info/entry_points.txt
ferelight-1.3.0.dist-info/top_level.txt
ferelight-1.3.0.dist-info/RECORD
