Metadata-Version: 2.4
Name: ferelight
Version: 1.3.0
Summary: Extremely lightweight and purpose-built feature extraction and retrieval engine (FERE).
Home-page: https://github.com/FEREorg/ferelight
Author: FERElight Team
Project-URL: Bug Tracker, https://github.com/FEREorg/ferelight/issues
Classifier: Programming Language :: Python :: 3
Classifier: License :: OSI Approved :: MIT License
Classifier: Operating System :: OS Independent
Requires-Python: >=3.9
License-File: LICENSE
Requires-Dist: connexion[swagger-ui]<3.0.0
Requires-Dist: swagger-ui-bundle>=0.0.2
Requires-Dist: python_dateutil>=2.6.0
Requires-Dist: setuptools>=21.0.0
Requires-Dist: Flask==2.2.5
Requires-Dist: psycopg2-binary==2.9.10
Requires-Dist: pgvector>=0.3.6
Requires-Dist: torch>=2.6.0
Requires-Dist: open_clip_torch>=2.29.0
Requires-Dist: transformers>=4.47.0
Dynamic: license-file
